[
  {
    "word": "قلم",
    "english": "Pen",
    "type": "noun",
    "image": "https://cdn-icons-png.flaticon.com/512/1995/1995574.png"
  },
  {
    "word": "كتاب",
    "english": "Book",
    "type": "noun",
    "image": "https://cdn-icons-png.flaticon.com/512/2949/2949878.png"
  },
  {
    "word": "ماء",
    "english": "Water",
    "type": "noun",
    "image": "https://cdn-icons-png.flaticon.com/512/728/728093.png"
  },
  {
    "word": "جميل",
    "english": "Beautiful",
    "type": "adjective",
    "image": "https://cdn-icons-png.flaticon.com/512/616/616408.png"
  },
  {
    "word": "سريع",
    "english": "Fast",
    "type": "adjective",
    "image": "https://cdn-icons-png.flaticon.com/512/615/615646.png"
  },
  {
    "word": "يكتب",
    "english": "Write",
    "type": "verb",
    "image": "https://cdn-icons-png.flaticon.com/512/1087/1087847.png"
  },
  {
    "word": "يقرأ",
    "english": "Read",
    "type": "verb",
    "image": "https://cdn-icons-png.flaticon.com/512/1087/1087895.png"
  },
  {
    "word": "يجري",
    "english": "Run",
    "type": "verb",
    "image": "https://cdn-icons-png.flaticon.com/512/1946/1946488.png"
  }
]